lockattrs/__init__.py
lockattrs/decorators.py
lockattrs-0.0.5.dist-info/LICENSE
lockattrs-0.0.5.dist-info/METADATA
lockattrs-0.0.5.dist-info/WHEEL
lockattrs-0.0.5.dist-info/top_level.txt
lockattrs-0.0.5.dist-info/RECORD
