Metadata-Version: 2.1
Name: lockattrs
Version: 0.0.5
Summary: Decorator used to lock class attributes.
Home-page: https://github.com/simphotonics/lockattrs
Author: D Reschner
Author-email: git@simphotonics.com
License: UNKNOWN
Project-URL: Bug Tracker, https://github.com/simphotonics/lockattrs/issues
Platform: UNKNOWN
Classifier: Programming Language :: Python :: 3
Classifier: License :: OSI Approved :: BSD License
Classifier: Operating System :: OS Independent
Requires-Python: >=3.8
License-File: LICENSE
